lolesports_api/__init__.py
lolesports_api/_base_client.py
lolesports_api/_client.py
lolesports_api/_compat.py
lolesports_api/_constants.py
lolesports_api/_exceptions.py
lolesports_api/_files.py
lolesports_api/_models.py
lolesports_api/_qs.py
lolesports_api/_resource.py
lolesports_api/_response.py
lolesports_api/_streaming.py
lolesports_api/_types.py
lolesports_api/_version.py
lolesports_api/py.typed
lolesports_api/_utils/__init__.py
lolesports_api/_utils/_compat.py
lolesports_api/_utils/_datetime_parse.py
lolesports_api/_utils/_logs.py
lolesports_api/_utils/_proxy.py
lolesports_api/_utils/_reflection.py
lolesports_api/_utils/_resources_proxy.py
lolesports_api/_utils/_streams.py
lolesports_api/_utils/_sync.py
lolesports_api/_utils/_transform.py
lolesports_api/_utils/_typing.py
lolesports_api/_utils/_utils.py
lolesports_api/lib/.keep
lolesports_api/resources/__init__.py
lolesports_api/resources/details.py
lolesports_api/resources/get_completed_events.py
lolesports_api/resources/get_event_details.py
lolesports_api/resources/get_games.py
lolesports_api/resources/get_leagues.py
lolesports_api/resources/get_live.py
lolesports_api/resources/get_schedule.py
lolesports_api/resources/get_standings.py
lolesports_api/resources/get_teams.py
lolesports_api/resources/get_tournaments_for_league.py
lolesports_api/resources/highlander_tournaments.py
lolesports_api/resources/leagues.py
lolesports_api/resources/nav_items.py
lolesports_api/resources/players.py
lolesports_api/resources/schedule_items.py
lolesports_api/resources/teams.py
lolesports_api/resources/videos.py
lolesports_api/resources/window.py
lolesports_api/types/__init__.py
lolesports_api/types/base_frame.py
lolesports_api/types/base_league.py
lolesports_api/types/base_match.py
lolesports_api/types/base_schedule_item.py
lolesports_api/types/base_strategy.py
lolesports_api/types/detail_retrieve_params.py
lolesports_api/types/detail_retrieve_response.py
lolesports_api/types/event_type.py
lolesports_api-1.0.1.dist-info/METADATA
lolesports_api-1.0.1.dist-info/WHEEL
lolesports_api-1.0.1.dist-info/licenses/LICENSE
lolesports_api-1.0.1.dist-info/RECORD
